piprec/__init__.py
piprec/__main__.py
piprec/association_rules_certainty_factor.db
piprec/association_rules_lift.db
piprec/bigram.model
piprec/extractor.py
piprec/lda.model
piprec/lda.model.expElogbeta.npy
piprec/lda.model.id2word
piprec/lda.model.state
piprec/lda_names_list.txt
piprec/library_summaries.json
piprec/recommender.py
piprec/rule_names_list.txt
piprec/similarity.py
piprec/topic_distribution.npy
piprec/trigram.model
piprec-1.0.0.dist-info/LICENSE
piprec-1.0.0.dist-info/METADATA
piprec-1.0.0.dist-info/WHEEL
piprec-1.0.0.dist-info/entry_points.txt
piprec-1.0.0.dist-info/top_level.txt
piprec-1.0.0.dist-info/RECORD
