Metadata-Version: 2.1
Name: piprec
Version: 1.0.0
Summary: Recommender system for Python libraries
Home-page: UNKNOWN
Author: Vladas
Author-email: 2262803m@student.gla.ac.uk
License: UNKNOWN
Project-URL: Source Code, https://github.com/VladasX/PipRec
Platform: UNKNOWN
Classifier: Development Status :: 5 - Production/Stable
Classifier: Environment :: Console
Classifier: Intended Audience :: Developers
Classifier: Operating System :: POSIX :: Linux
Classifier: Operating System :: Microsoft :: Windows
Classifier: Programming Language :: Python :: 3
Classifier: Programming Language :: Python :: 3.5
Classifier: Programming Language :: Python :: 3.6
Classifier: Programming Language :: Python :: 3.7
Classifier: Programming Language :: Python :: 3.8
Classifier: Topic :: Software Development
Requires-Python: >=3
Requires-Dist: requests
Requires-Dist: argparse
Requires-Dist: gensim
Requires-Dist: nltk
Requires-Dist: scipy (<=1.3.2)
Requires-Dist: numpy (>=1.15.0)
Requires-Dist: anytree
Requires-Dist: tabulate
Requires-Dist: spacy (>=2.2.2)
Requires-Dist: beautifulsoup4
Requires-Dist: en-core-web-sm-mirror
